MANIFEST.in
README.rst
setup.py
pillowncase/__init__.py
pillowncase/__main__.py
pillowncase/pncase.py
pillowncase.egg-info/PKG-INFO
pillowncase.egg-info/SOURCES.txt
pillowncase.egg-info/dependency_links.txt
pillowncase.egg-info/entry_points.txt
pillowncase.egg-info/not-zip-safe
pillowncase.egg-info/requires.txt
pillowncase.egg-info/top_level.txt
pillowncase/files/__init__.py
pillowncase/files/bitshift.zip
pillowncase/files/flowers.jpg
pillowncase/files/horse.jpg
pillowncase/files/katie.jpg
pillowncase/files/kitten.jpg
pillowncase/files/pNcase.png
pillowncase/files/pNcase_test.txt
pillowncase/files/pg29809.txt
pillowncase/files/__pycache__/__init__.cpython-35.pyc