Metadata-Version: 1.1
Name: pillowncase
Version: 0.3
Summary: Store and retreive any file data in any image
Home-page: https://github.com/ArchageXIII/pillowncase
Author: Mark Edwards
Author-email: mark.3dwards@gmail.com
License: GNU GPL
Download-URL: https://github.com/ArchageXIII/pillowncase
Platform: windows
Platform: linux
